{
  "name": {
    "first": "Rakesh",
    "middle": null,
    "last": "Dulam"
  },
  "position": [
    "PhD Student"
  ],
  "research": [
    "Reinforcement Learning",
    "Continual Learning"
  ],
  "introduction": "Rakesh is a MS student in the Department of Computer Science advised by Dr. Jake Lee. His research focuses on evaluating continual learning algorithms in diverse environments, assisting Ben.",
  "contact": {
    "email": [
      "cdulam@charlotte.edu"
    ],
    "address": "Room 437, Woodward Hall",
    "website": null
  },
  "photo": "/photos/rakesh.jpg"
}
